django_ses/__init__.py
django_ses/admin.py
django_ses/apps.py
django_ses/conf.py
django_ses/deprecation.py
django_ses/inbound.py
django_ses/management/__init__.py
django_ses/management/commands/__init__.py
django_ses/management/commands/blacklist.py
django_ses/management/commands/get_ses_statistics.py
django_ses/management/commands/ses_email_address.py
django_ses/migrations/0001_initial.py
django_ses/migrations/0002_blacklistedemail.py
django_ses/migrations/__init__.py
django_ses/models.py
django_ses/signals.py
django_ses/templates/django_ses/send_stats.html
django_ses/urls.py
django_ses/utils.py
django_ses/views.py
django_ses-4.6.0.dist-info/METADATA
django_ses-4.6.0.dist-info/WHEEL
django_ses-4.6.0.dist-info/licenses/LICENSE
django_ses-4.6.0.dist-info/RECORD
