Metadata-Version: 2.4
Name: django-ses
Version: 4.6.0
Summary: A Django email backend for Amazon's Simple Email Service (SES)
License: MIT
License-File: LICENSE
Author: Harry Marr
Author-email: harry@hmarr.com
Requires-Python: >=3.8,<4.0
Classifier: Development Status :: 5 - Production/Stable
Classifier: Framework :: Django
Classifier: Framework :: Django :: 3.2
Classifier: Framework :: Django :: 4.2
Classifier: Framework :: Django :: 5.2
Classifier: Framework :: Django :: 6.0
Classifier: Intended Audience :: Developers
Classifier: License :: OSI Approved :: MIT License
Classifier: Operating System :: OS Independent
Classifier: Programming Language :: Python
Classifier: Programming Language :: Python :: 3
Classifier: Programming Language :: Python :: 3.8
Classifier: Programming Language :: Python :: 3.9
Classifier: Programming Language :: Python :: 3.10
Classifier: Programming Language :: Python :: 3.11
Classifier: Programming Language :: Python :: 3.12
Classifier: Programming Language :: Python :: 3.13
Classifier: Programming Language :: Python :: 3.14
Classifier: Topic :: Software Development :: Libraries :: Python Modules
Provides-Extra: bounce
Provides-Extra: events
Requires-Dist: backports-zoneinfo (>=0.2.1) ; python_version < "3.9"
Requires-Dist: boto3 (>=1.0.0)
Requires-Dist: cryptography (>=36.0.2) ; extra == "bounce" or extra == "events"
Requires-Dist: django (>=3.2)
Requires-Dist: importlib-metadata (>=1) ; python_version < "3.8"
Requires-Dist: requests (>=2.32.1) ; extra == "bounce" or extra == "events"
Project-URL: Bugtracker, https://github.com/django-ses/django-ses/issues
Project-URL: Changelog, https://github.com/django-ses/django-ses/blob/main/CHANGES.md
Project-URL: Documentation, https://github.com/django-ses/django-ses/blob/main/README.rst
Project-URL: Homepage, https://github.com/django-ses/django-ses
Project-URL: Repository, https://github.com/django-ses/django-ses
